{"UtilityTest_testGetTelemetryClient": ["smpl.ordering.UtilityTest", "smpl.ordering.Utility", "smpl.ordering.OrderingConfiguration", "smpl.ordering.ConfigurationRule", "smpl.ordering.TestOrderingConfiguration", "smpl.ordering.PropertyHelper", "smpl.ordering.repositories.RepositoryFactory", "smpl.ordering.repositories.mock.MockCatalogItemsRepository", "smpl.ordering.models.CatalogItem", "smpl.ordering.repositories.mock.MockDealersRepository", "smpl.ordering.repositories.mock.MockQuoteRepository", "smpl.ordering.repositories.mock.MockOrderRepository", "smpl.ordering.repositories.mock.MockShipmentRepository", "smpl.ordering.repositories.mongodb.MongoCatalogItemsRepository", "smpl.ordering.repositories.mongodb.MongoOperationsWithRetry", "smpl.ordering.repositories.mongodb.MongoDealersRepository", "smpl.ordering.repositories.mongodb.MongoQuoteRepository", "smpl.ordering.repositories.mongodb.MongoOrderRepository", "smpl.ordering.repositories.mongodb.MongoShipmentRepository"], "UtilityTest_testIsNullOrEmpty": ["smpl.ordering.UtilityTest", "smpl.ordering.Utility"], "MockOrderRepositoryTest_testGetOrder": ["smpl.ordering.repositories.mock.test.MockOrderRepositoryTest", "smpl.ordering.repositories.RepositoryFactory", "smpl.ordering.OrderingConfiguration", "smpl.ordering.repositories.mock.MockCatalogItemsRepository", "smpl.ordering.models.CatalogItem", "smpl.ordering.repositories.mock.MockDealersRepository", "smpl.ordering.repositories.mock.MockQuoteRepository", "smpl.ordering.repositories.mock.MockOrderRepository", "smpl.ordering.repositories.mock.MockShipmentRepository", "smpl.ordering.repositories.mongodb.MongoCatalogItemsRepository", "smpl.ordering.repositories.mongodb.MongoOperationsWithRetry", "smpl.ordering.repositories.mongodb.MongoDealersRepository", "smpl.ordering.repositories.mongodb.MongoQuoteRepository", "smpl.ordering.repositories.mongodb.MongoOrderRepository", "smpl.ordering.repositories.mongodb.MongoShipmentRepository", "smpl.ordering.repositories.OrderRepositoryTest", "smpl.ordering.repositories.DealersRepositoryTest", "smpl.ordering.models.DealerInfo", "smpl.ordering.repositories.QuoteRepositoryTest", "smpl.ordering.models.Quote", "smpl.ordering.models.QuoteItemInfo", "smpl.ordering.models.Order"], "MockOrderRepositoryTest_testGetOrdersByDealerName": ["smpl.ordering.models.Order", "smpl.ordering.repositories.mock.MockOrderRepository", "smpl.ordering.repositories.OrderRepositoryTest", "smpl.ordering.repositories.mock.test.MockOrderRepositoryTest", "smpl.ordering.repositories.RepositoryFactory", "smpl.ordering.OrderingConfiguration", "smpl.ordering.repositories.mock.MockCatalogItemsRepository", "smpl.ordering.models.CatalogItem", "smpl.ordering.repositories.mock.MockDealersRepository", "smpl.ordering.repositories.mock.MockQuoteRepository", "smpl.ordering.repositories.mock.MockShipmentRepository", "smpl.ordering.repositories.mongodb.MongoCatalogItemsRepository", "smpl.ordering.repositories.mongodb.MongoOperationsWithRetry", "smpl.ordering.repositories.mongodb.MongoDealersRepository", "smpl.ordering.repositories.mongodb.MongoQuoteRepository", "smpl.ordering.repositories.mongodb.MongoOrderRepository", "smpl.ordering.repositories.mongodb.MongoShipmentRepository", "smpl.ordering.repositories.DealersRepositoryTest", "smpl.ordering.models.DealerInfo", "smpl.ordering.repositories.QuoteRepositoryTest", "smpl.ordering.models.Quote", "smpl.ordering.models.QuoteItemInfo"], "MockOrderRepositoryTest_testUpdateOrder": ["smpl.ordering.repositories.mock.test.MockOrderRepositoryTest", "smpl.ordering.repositories.RepositoryFactory", "smpl.ordering.OrderingConfiguration", "smpl.ordering.repositories.mock.MockCatalogItemsRepository", "smpl.ordering.models.CatalogItem", "smpl.ordering.repositories.mock.MockDealersRepository", "smpl.ordering.repositories.mock.MockQuoteRepository", "smpl.ordering.repositories.mock.MockOrderRepository", "smpl.ordering.repositories.mock.MockShipmentRepository", "smpl.ordering.repositories.mongodb.MongoCatalogItemsRepository", "smpl.ordering.repositories.mongodb.MongoOperationsWithRetry", "smpl.ordering.repositories.mongodb.MongoDealersRepository", "smpl.ordering.repositories.mongodb.MongoQuoteRepository", "smpl.ordering.repositories.mongodb.MongoOrderRepository", "smpl.ordering.repositories.mongodb.MongoShipmentRepository", "smpl.ordering.repositories.OrderRepositoryTest", "smpl.ordering.repositories.DealersRepositoryTest", "smpl.ordering.models.DealerInfo", "smpl.ordering.repositories.QuoteRepositoryTest", "smpl.ordering.models.Quote", "smpl.ordering.models.QuoteItemInfo", "smpl.ordering.models.Order", "smpl.ordering.models.OrderEventInfo"], "MockOrderRepositoryTest_testCreateOrder": ["smpl.ordering.models.Order", "smpl.ordering.repositories.mock.MockOrderRepository", "smpl.ordering.models.OrderEventInfo", "smpl.ordering.repositories.OrderRepositoryTest", "smpl.ordering.repositories.mock.test.MockOrderRepositoryTest", "smpl.ordering.repositories.RepositoryFactory", "smpl.ordering.OrderingConfiguration", "smpl.ordering.repositories.mock.MockCatalogItemsRepository", "smpl.ordering.models.CatalogItem", "smpl.ordering.repositories.mock.MockDealersRepository", "smpl.ordering.repositories.mock.MockQuoteRepository", "smpl.ordering.repositories.mock.MockShipmentRepository", "smpl.ordering.repositories.mongodb.MongoCatalogItemsRepository", "smpl.ordering.repositories.mongodb.MongoOperationsWithRetry", "smpl.ordering.repositories.mongodb.MongoDealersRepository", "smpl.ordering.repositories.mongodb.MongoQuoteRepository", "smpl.ordering.repositories.mongodb.MongoOrderRepository", "smpl.ordering.repositories.mongodb.MongoShipmentRepository", "smpl.ordering.repositories.DealersRepositoryTest", "smpl.ordering.models.DealerInfo", "smpl.ordering.repositories.QuoteRepositoryTest", "smpl.ordering.models.Quote", "smpl.ordering.models.QuoteItemInfo", "smpl.ordering.BadRequestException", "smpl.ordering.ConflictingRequestException"], "MockOrderRepositoryTest_testUpdateOrder1": ["smpl.ordering.models.Order", "smpl.ordering.BadRequestException", "smpl.ordering.ConflictingRequestException", "smpl.ordering.repositories.mock.MockOrderRepository", "smpl.ordering.repositories.OrderRepositoryTest", "smpl.ordering.repositories.mock.test.MockOrderRepositoryTest", "smpl.ordering.repositories.RepositoryFactory", "smpl.ordering.OrderingConfiguration", "smpl.ordering.repositories.mock.MockCatalogItemsRepository", "smpl.ordering.models.CatalogItem", "smpl.ordering.repositories.mock.MockDealersRepository", "smpl.ordering.repositories.mock.MockQuoteRepository", "smpl.ordering.repositories.mock.MockShipmentRepository", "smpl.ordering.repositories.mongodb.MongoCatalogItemsRepository", "smpl.ordering.repositories.mongodb.MongoOperationsWithRetry", "smpl.ordering.repositories.mongodb.MongoDealersRepository", "smpl.ordering.repositories.mongodb.MongoQuoteRepository", "smpl.ordering.repositories.mongodb.MongoOrderRepository", "smpl.ordering.repositories.mongodb.MongoShipmentRepository", "smpl.ordering.repositories.DealersRepositoryTest", "smpl.ordering.models.DealerInfo", "smpl.ordering.repositories.QuoteRepositoryTest", "smpl.ordering.models.Quote", "smpl.ordering.models.QuoteItemInfo", "smpl.ordering.models.OrderEventInfo", "smpl.ordering.models.OrderUpdateInfo"], "MockOrderRepositoryTest_testGetOrdersByStatus": ["smpl.ordering.repositories.mock.MockOrderRepository", "smpl.ordering.models.Order", "smpl.ordering.models.OrderUpdateInfo", "smpl.ordering.models.OrderEventInfo", "smpl.ordering.repositories.OrderRepositoryTest", "smpl.ordering.repositories.mock.test.MockOrderRepositoryTest", "smpl.ordering.repositories.RepositoryFactory", "smpl.ordering.OrderingConfiguration", "smpl.ordering.repositories.mock.MockCatalogItemsRepository", "smpl.ordering.models.CatalogItem", "smpl.ordering.repositories.mock.MockDealersRepository", "smpl.ordering.repositories.mock.MockQuoteRepository", "smpl.ordering.repositories.mock.MockShipmentRepository", "smpl.ordering.repositories.mongodb.MongoCatalogItemsRepository", "smpl.ordering.repositories.mongodb.MongoOperationsWithRetry", "smpl.ordering.repositories.mongodb.MongoDealersRepository", "smpl.ordering.repositories.mongodb.MongoQuoteRepository", "smpl.ordering.repositories.mongodb.MongoOrderRepository", "smpl.ordering.repositories.mongodb.MongoShipmentRepository", "smpl.ordering.repositories.DealersRepositoryTest", "smpl.ordering.models.DealerInfo", "smpl.ordering.repositories.QuoteRepositoryTest", "smpl.ordering.models.Quote", "smpl.ordering.models.QuoteItemInfo"], "MockOrderRepositoryTest_testGetOrdersByQuoteId": ["smpl.ordering.repositories.mock.MockQuoteRepository", "smpl.ordering.repositories.mock.MockOrderRepository", "smpl.ordering.models.Order", "smpl.ordering.repositories.OrderRepositoryTest", "smpl.ordering.repositories.mock.test.MockOrderRepositoryTest", "smpl.ordering.repositories.RepositoryFactory", "smpl.ordering.OrderingConfiguration", "smpl.ordering.repositories.mock.MockCatalogItemsRepository", "smpl.ordering.models.CatalogItem", "smpl.ordering.repositories.mock.MockDealersRepository", "smpl.ordering.repositories.mock.MockShipmentRepository", "smpl.ordering.repositories.mongodb.MongoCatalogItemsRepository", "smpl.ordering.repositories.mongodb.MongoOperationsWithRetry", "smpl.ordering.repositories.mongodb.MongoDealersRepository", "smpl.ordering.repositories.mongodb.MongoQuoteRepository", "smpl.ordering.repositories.mongodb.MongoOrderRepository", "smpl.ordering.repositories.mongodb.MongoShipmentRepository", "smpl.ordering.repositories.DealersRepositoryTest", "smpl.ordering.models.DealerInfo", "smpl.ordering.repositories.QuoteRepositoryTest", "smpl.ordering.models.Quote", "smpl.ordering.models.QuoteItemInfo"], "MockOrderRepositoryTest_testHasOrder": ["smpl.ordering.repositories.mock.MockDealersRepository", "smpl.ordering.models.Quote", "smpl.ordering.repositories.mock.MockQuoteRepository", "smpl.ordering.repositories.mock.MockOrderRepository", "smpl.ordering.models.Order", "smpl.ordering.repositories.QuoteRepositoryTest", "smpl.ordering.models.QuoteItemInfo", "smpl.ordering.models.DealerInfo", "smpl.ordering.repositories.OrderRepositoryTest", "smpl.ordering.repositories.mock.test.MockOrderRepositoryTest", "smpl.ordering.repositories.RepositoryFactory", "smpl.ordering.OrderingConfiguration", "smpl.ordering.repositories.mock.MockCatalogItemsRepository", "smpl.ordering.models.CatalogItem", "smpl.ordering.repositories.mock.MockShipmentRepository", "smpl.ordering.repositories.mongodb.MongoCatalogItemsRepository", "smpl.ordering.repositories.mongodb.MongoOperationsWithRetry", "smpl.ordering.repositories.mongodb.MongoDealersRepository", "smpl.ordering.repositories.mongodb.MongoQuoteRepository", "smpl.ordering.repositories.mongodb.MongoOrderRepository", "smpl.ordering.repositories.mongodb.MongoShipmentRepository", "smpl.ordering.repositories.DealersRepositoryTest"], "MockCatalogItemsRepositoryTest_testRemoveCatalogItem": ["smpl.ordering.repositories.mock.test.MockCatalogItemsRepositoryTest", "smpl.ordering.repositories.RepositoryFactory", "smpl.ordering.OrderingConfiguration", "smpl.ordering.repositories.mock.MockCatalogItemsRepository", "smpl.ordering.models.CatalogItem", "smpl.ordering.repositories.mock.MockDealersRepository", "smpl.ordering.repositories.mock.MockQuoteRepository", "smpl.ordering.repositories.mock.MockOrderRepository", "smpl.ordering.repositories.mock.MockShipmentRepository", "smpl.ordering.repositories.mongodb.MongoCatalogItemsRepository", "smpl.ordering.repositories.mongodb.MongoOperationsWithRetry", "smpl.ordering.repositories.mongodb.MongoDealersRepository", "smpl.ordering.repositories.mongodb.MongoQuoteRepository", "smpl.ordering.repositories.mongodb.MongoOrderRepository", "smpl.ordering.repositories.mongodb.MongoShipmentRepository", "smpl.ordering.repositories.CatalogItemsRepositoryTest"], "MockCatalogItemsRepositoryTest_testGetCatalogItems": ["smpl.ordering.repositories.mock.test.MockCatalogItemsRepositoryTest", "smpl.ordering.repositories.RepositoryFactory", "smpl.ordering.OrderingConfiguration", "smpl.ordering.repositories.mock.MockCatalogItemsRepository", "smpl.ordering.models.CatalogItem", "smpl.ordering.repositories.mock.MockDealersRepository", "smpl.ordering.repositories.mock.MockQuoteRepository", "smpl.ordering.repositories.mock.MockOrderRepository", "smpl.ordering.repositories.mock.MockShipmentRepository", "smpl.ordering.repositories.mongodb.MongoCatalogItemsRepository", "smpl.ordering.repositories.mongodb.MongoOperationsWithRetry", "smpl.ordering.repositories.mongodb.MongoDealersRepository", "smpl.ordering.repositories.mongodb.MongoQuoteRepository", "smpl.ordering.repositories.mongodb.MongoOrderRepository", "smpl.ordering.repositories.mongodb.MongoShipmentRepository", "smpl.ordering.repositories.CatalogItemsRepositoryTest"], "MockCatalogItemsRepositoryTest_testGetCatalogItem": ["smpl.ordering.models.CatalogItem", "smpl.ordering.repositories.mock.MockCatalogItemsRepository", "smpl.ordering.repositories.CatalogItemsRepositoryTest", "smpl.ordering.repositories.mock.test.MockCatalogItemsRepositoryTest", "smpl.ordering.repositories.RepositoryFactory", "smpl.ordering.OrderingConfiguration", "smpl.ordering.repositories.mock.MockDealersRepository", "smpl.ordering.repositories.mock.MockQuoteRepository", "smpl.ordering.repositories.mock.MockOrderRepository", "smpl.ordering.repositories.mock.MockShipmentRepository", "smpl.ordering.repositories.mongodb.MongoCatalogItemsRepository", "smpl.ordering.repositories.mongodb.MongoOperationsWithRetry", "smpl.ordering.repositories.mongodb.MongoDealersRepository", "smpl.ordering.repositories.mongodb.MongoQuoteRepository", "smpl.ordering.repositories.mongodb.MongoOrderRepository", "smpl.ordering.repositories.mongodb.MongoShipmentRepository"], "MockCatalogItemsRepositoryTest_testUpsertCatalogItem": ["smpl.ordering.repositories.mock.MockCatalogItemsRepository", "smpl.ordering.models.CatalogItem", "smpl.ordering.repositories.CatalogItemsRepositoryTest", "smpl.ordering.repositories.mock.test.MockCatalogItemsRepositoryTest", "smpl.ordering.repositories.RepositoryFactory", "smpl.ordering.OrderingConfiguration", "smpl.ordering.repositories.mock.MockDealersRepository", "smpl.ordering.repositories.mock.MockQuoteRepository", "smpl.ordering.repositories.mock.MockOrderRepository", "smpl.ordering.repositories.mock.MockShipmentRepository", "smpl.ordering.repositories.mongodb.MongoCatalogItemsRepository", "smpl.ordering.repositories.mongodb.MongoOperationsWithRetry", "smpl.ordering.repositories.mongodb.MongoDealersRepository", "smpl.ordering.repositories.mongodb.MongoQuoteRepository", "smpl.ordering.repositories.mongodb.MongoOrderRepository", "smpl.ordering.repositories.mongodb.MongoShipmentRepository"], "MockDealersRepositoryTest_testUpsertDealer": ["smpl.ordering.repositories.mock.test.MockDealersRepositoryTest", "smpl.ordering.repositories.RepositoryFactory", "smpl.ordering.OrderingConfiguration", "smpl.ordering.repositories.mock.MockCatalogItemsRepository", "smpl.ordering.models.CatalogItem", "smpl.ordering.repositories.mock.MockDealersRepository", "smpl.ordering.repositories.mock.MockQuoteRepository", "smpl.ordering.repositories.mock.MockOrderRepository", "smpl.ordering.repositories.mock.MockShipmentRepository", "smpl.ordering.repositories.mongodb.MongoCatalogItemsRepository", "smpl.ordering.repositories.mongodb.MongoOperationsWithRetry", "smpl.ordering.repositories.mongodb.MongoDealersRepository", "smpl.ordering.repositories.mongodb.MongoQuoteRepository", "smpl.ordering.repositories.mongodb.MongoOrderRepository", "smpl.ordering.repositories.mongodb.MongoShipmentRepository", "smpl.ordering.repositories.DealersRepositoryTest", "smpl.ordering.models.DealerInfo"], "MockDealersRepositoryTest_testRemoveDealer": ["smpl.ordering.repositories.mock.test.MockDealersRepositoryTest", "smpl.ordering.repositories.RepositoryFactory", "smpl.ordering.OrderingConfiguration", "smpl.ordering.repositories.mock.MockCatalogItemsRepository", "smpl.ordering.models.CatalogItem", "smpl.ordering.repositories.mock.MockDealersRepository", "smpl.ordering.repositories.mock.MockQuoteRepository", "smpl.ordering.repositories.mock.MockOrderRepository", "smpl.ordering.repositories.mock.MockShipmentRepository", "smpl.ordering.repositories.mongodb.MongoCatalogItemsRepository", "smpl.ordering.repositories.mongodb.MongoOperationsWithRetry", "smpl.ordering.repositories.mongodb.MongoDealersRepository", "smpl.ordering.repositories.mongodb.MongoQuoteRepository", "smpl.ordering.repositories.mongodb.MongoOrderRepository", "smpl.ordering.repositories.mongodb.MongoShipmentRepository", "smpl.ordering.repositories.DealersRepositoryTest", "smpl.ordering.models.DealerInfo"], "MockDealersRepositoryTest_testGetDealer": ["smpl.ordering.repositories.mock.test.MockDealersRepositoryTest", "smpl.ordering.repositories.RepositoryFactory", "smpl.ordering.OrderingConfiguration", "smpl.ordering.repositories.mock.MockCatalogItemsRepository", "smpl.ordering.models.CatalogItem", "smpl.ordering.repositories.mock.MockDealersRepository", "smpl.ordering.repositories.mock.MockQuoteRepository", "smpl.ordering.repositories.mock.MockOrderRepository", "smpl.ordering.repositories.mock.MockShipmentRepository", "smpl.ordering.repositories.mongodb.MongoCatalogItemsRepository", "smpl.ordering.repositories.mongodb.MongoOperationsWithRetry", "smpl.ordering.repositories.mongodb.MongoDealersRepository", "smpl.ordering.repositories.mongodb.MongoQuoteRepository", "smpl.ordering.repositories.mongodb.MongoOrderRepository", "smpl.ordering.repositories.mongodb.MongoShipmentRepository", "smpl.ordering.repositories.DealersRepositoryTest", "smpl.ordering.models.DealerInfo"], "MockDealersRepositoryTest_testGetDealers": ["smpl.ordering.repositories.mock.MockDealersRepository", "smpl.ordering.repositories.DealersRepositoryTest", "smpl.ordering.repositories.mock.test.MockDealersRepositoryTest", "smpl.ordering.models.DealerInfo", "smpl.ordering.repositories.RepositoryFactory", "smpl.ordering.OrderingConfiguration", "smpl.ordering.repositories.mock.MockCatalogItemsRepository", "smpl.ordering.models.CatalogItem", "smpl.ordering.repositories.mock.MockQuoteRepository", "smpl.ordering.repositories.mock.MockOrderRepository", "smpl.ordering.repositories.mock.MockShipmentRepository", "smpl.ordering.repositories.mongodb.MongoCatalogItemsRepository", "smpl.ordering.repositories.mongodb.MongoOperationsWithRetry", "smpl.ordering.repositories.mongodb.MongoDealersRepository", "smpl.ordering.repositories.mongodb.MongoQuoteRepository", "smpl.ordering.repositories.mongodb.MongoOrderRepository", "smpl.ordering.repositories.mongodb.MongoShipmentRepository"], "MockShipmentRepositoryTest_testGetShipments": ["smpl.ordering.repositories.mock.test.MockShipmentRepositoryTest", "smpl.ordering.repositories.RepositoryFactory", "smpl.ordering.OrderingConfiguration", "smpl.ordering.repositories.mock.MockCatalogItemsRepository", "smpl.ordering.models.CatalogItem", "smpl.ordering.repositories.mock.MockDealersRepository", "smpl.ordering.repositories.mock.MockQuoteRepository", "smpl.ordering.repositories.mock.MockOrderRepository", "smpl.ordering.repositories.mock.MockShipmentRepository", "smpl.ordering.repositories.mongodb.MongoCatalogItemsRepository", "smpl.ordering.repositories.mongodb.MongoOperationsWithRetry", "smpl.ordering.repositories.mongodb.MongoDealersRepository", "smpl.ordering.repositories.mongodb.MongoQuoteRepository", "smpl.ordering.repositories.mongodb.MongoOrderRepository", "smpl.ordering.repositories.mongodb.MongoShipmentRepository", "smpl.ordering.repositories.ShipmentRepositoryTest", "smpl.ordering.repositories.DealersRepositoryTest", "smpl.ordering.models.DealerInfo", "smpl.ordering.repositories.QuoteRepositoryTest", "smpl.ordering.models.Quote", "smpl.ordering.models.QuoteItemInfo", "smpl.ordering.models.Order", "smpl.ordering.models.ShipmentRecord", "smpl.ordering.models.PhoneInfo", "smpl.ordering.models.DeliveryAddress"], "MockShipmentRepositoryTest_testUpdateShipment": ["smpl.ordering.models.Order", "smpl.ordering.repositories.mock.MockOrderRepository", "smpl.ordering.models.ShipmentRecord", "smpl.ordering.repositories.mock.MockShipmentRepository", "smpl.ordering.repositories.ShipmentRepositoryTest", "smpl.ordering.repositories.mock.test.MockShipmentRepositoryTest", "smpl.ordering.repositories.RepositoryFactory", "smpl.ordering.OrderingConfiguration", "smpl.ordering.repositories.mock.MockCatalogItemsRepository", "smpl.ordering.models.CatalogItem", "smpl.ordering.repositories.mock.MockDealersRepository", "smpl.ordering.repositories.mock.MockQuoteRepository", "smpl.ordering.repositories.mongodb.MongoCatalogItemsRepository", "smpl.ordering.repositories.mongodb.MongoOperationsWithRetry", "smpl.ordering.repositories.mongodb.MongoDealersRepository", "smpl.ordering.repositories.mongodb.MongoQuoteRepository", "smpl.ordering.repositories.mongodb.MongoOrderRepository", "smpl.ordering.repositories.mongodb.MongoShipmentRepository", "smpl.ordering.repositories.DealersRepositoryTest", "smpl.ordering.models.DealerInfo", "smpl.ordering.repositories.QuoteRepositoryTest", "smpl.ordering.models.Quote", "smpl.ordering.models.QuoteItemInfo", "smpl.ordering.models.PhoneInfo", "smpl.ordering.models.DeliveryAddress", "smpl.ordering.models.ShipmentEventInfo"], "MockShipmentRepositoryTest_testCreateShipment": ["smpl.ordering.models.Order", "smpl.ordering.repositories.mock.MockOrderRepository", "smpl.ordering.repositories.QuoteRepositoryTest", "smpl.ordering.models.Quote", "smpl.ordering.models.QuoteItemInfo", "smpl.ordering.repositories.mock.MockQuoteRepository", "smpl.ordering.repositories.mock.MockDealersRepository", "smpl.ordering.models.DealerInfo", "smpl.ordering.repositories.ShipmentRepositoryTest", "smpl.ordering.repositories.mock.test.MockShipmentRepositoryTest", "smpl.ordering.repositories.mock.MockShipmentRepository", "smpl.ordering.models.ShipmentRecord", "smpl.ordering.models.ShipmentEventInfo", "smpl.ordering.repositories.RepositoryFactory", "smpl.ordering.OrderingConfiguration", "smpl.ordering.repositories.mock.MockCatalogItemsRepository", "smpl.ordering.models.CatalogItem", "smpl.ordering.repositories.mongodb.MongoCatalogItemsRepository", "smpl.ordering.repositories.mongodb.MongoOperationsWithRetry", "smpl.ordering.repositories.mongodb.MongoDealersRepository", "smpl.ordering.repositories.mongodb.MongoQuoteRepository", "smpl.ordering.repositories.mongodb.MongoOrderRepository", "smpl.ordering.repositories.mongodb.MongoShipmentRepository", "smpl.ordering.repositories.DealersRepositoryTest", "smpl.ordering.models.PhoneInfo", "smpl.ordering.models.DeliveryAddress", "smpl.ordering.BadRequestException"], "MockShipmentRepositoryTest_testAddEvent": ["smpl.ordering.models.ShipmentRecord", "smpl.ordering.models.DeliveryAddress", "smpl.ordering.repositories.ShipmentRepositoryTest", "smpl.ordering.repositories.mock.MockShipmentRepository", "smpl.ordering.repositories.mock.MockOrderRepository", "smpl.ordering.models.Order", "smpl.ordering.BadRequestException", "smpl.ordering.models.PhoneInfo", "smpl.ordering.repositories.mock.test.MockShipmentRepositoryTest", "smpl.ordering.repositories.RepositoryFactory", "smpl.ordering.OrderingConfiguration", "smpl.ordering.repositories.mock.MockCatalogItemsRepository", "smpl.ordering.models.CatalogItem", "smpl.ordering.repositories.mock.MockDealersRepository", "smpl.ordering.repositories.mock.MockQuoteRepository", "smpl.ordering.repositories.mongodb.MongoCatalogItemsRepository", "smpl.ordering.repositories.mongodb.MongoOperationsWithRetry", "smpl.ordering.repositories.mongodb.MongoDealersRepository", "smpl.ordering.repositories.mongodb.MongoQuoteRepository", "smpl.ordering.repositories.mongodb.MongoOrderRepository", "smpl.ordering.repositories.mongodb.MongoShipmentRepository", "smpl.ordering.repositories.DealersRepositoryTest", "smpl.ordering.models.DealerInfo", "smpl.ordering.repositories.QuoteRepositoryTest", "smpl.ordering.models.Quote", "smpl.ordering.models.QuoteItemInfo", "smpl.ordering.models.ShipmentEventInfo"], "MockShipmentRepositoryTest_testGetShipmentById": ["smpl.ordering.models.Order", "smpl.ordering.repositories.mock.MockOrderRepository", "smpl.ordering.repositories.QuoteRepositoryTest", "smpl.ordering.models.Quote", "smpl.ordering.models.QuoteItemInfo", "smpl.ordering.repositories.mock.MockQuoteRepository", "smpl.ordering.repositories.mock.MockDealersRepository", "smpl.ordering.models.DealerInfo", "smpl.ordering.repositories.ShipmentRepositoryTest", "smpl.ordering.repositories.mock.test.MockShipmentRepositoryTest", "smpl.ordering.repositories.mock.MockShipmentRepository", "smpl.ordering.models.ShipmentRecord", "smpl.ordering.models.ShipmentEventInfo", "smpl.ordering.repositories.RepositoryFactory", "smpl.ordering.OrderingConfiguration", "smpl.ordering.repositories.mock.MockCatalogItemsRepository", "smpl.ordering.models.CatalogItem", "smpl.ordering.repositories.mongodb.MongoCatalogItemsRepository", "smpl.ordering.repositories.mongodb.MongoOperationsWithRetry", "smpl.ordering.repositories.mongodb.MongoDealersRepository", "smpl.ordering.repositories.mongodb.MongoQuoteRepository", "smpl.ordering.repositories.mongodb.MongoOrderRepository", "smpl.ordering.repositories.mongodb.MongoShipmentRepository", "smpl.ordering.repositories.DealersRepositoryTest", "smpl.ordering.models.PhoneInfo", "smpl.ordering.models.DeliveryAddress"], "MockQuoteRepositoryTest_testGetQuote": ["smpl.ordering.repositories.mock.test.MockQuoteRepositoryTest", "smpl.ordering.repositories.RepositoryFactory", "smpl.ordering.OrderingConfiguration", "smpl.ordering.repositories.mock.MockCatalogItemsRepository", "smpl.ordering.models.CatalogItem", "smpl.ordering.repositories.mock.MockDealersRepository", "smpl.ordering.repositories.mock.MockQuoteRepository", "smpl.ordering.repositories.mock.MockOrderRepository", "smpl.ordering.repositories.mock.MockShipmentRepository", "smpl.ordering.repositories.mongodb.MongoCatalogItemsRepository", "smpl.ordering.repositories.mongodb.MongoOperationsWithRetry", "smpl.ordering.repositories.mongodb.MongoDealersRepository", "smpl.ordering.repositories.mongodb.MongoQuoteRepository", "smpl.ordering.repositories.mongodb.MongoOrderRepository", "smpl.ordering.repositories.mongodb.MongoShipmentRepository", "smpl.ordering.repositories.QuoteRepositoryTest", "smpl.ordering.repositories.DealersRepositoryTest", "smpl.ordering.models.DealerInfo", "smpl.ordering.models.Quote", "smpl.ordering.models.QuoteItemInfo"], "MockQuoteRepositoryTest_testUpdateQuote": ["smpl.ordering.repositories.mock.test.MockQuoteRepositoryTest", "smpl.ordering.repositories.RepositoryFactory", "smpl.ordering.OrderingConfiguration", "smpl.ordering.repositories.mock.MockCatalogItemsRepository", "smpl.ordering.models.CatalogItem", "smpl.ordering.repositories.mock.MockDealersRepository", "smpl.ordering.repositories.mock.MockQuoteRepository", "smpl.ordering.repositories.mock.MockOrderRepository", "smpl.ordering.repositories.mock.MockShipmentRepository", "smpl.ordering.repositories.mongodb.MongoCatalogItemsRepository", "smpl.ordering.repositories.mongodb.MongoOperationsWithRetry", "smpl.ordering.repositories.mongodb.MongoDealersRepository", "smpl.ordering.repositories.mongodb.MongoQuoteRepository", "smpl.ordering.repositories.mongodb.MongoOrderRepository", "smpl.ordering.repositories.mongodb.MongoShipmentRepository", "smpl.ordering.repositories.QuoteRepositoryTest", "smpl.ordering.repositories.DealersRepositoryTest", "smpl.ordering.models.DealerInfo", "smpl.ordering.models.Quote", "smpl.ordering.models.QuoteItemInfo"], "MockQuoteRepositoryTest_testCreateQuote": ["smpl.ordering.repositories.QuoteRepositoryTest", "smpl.ordering.repositories.mock.test.MockQuoteRepositoryTest", "smpl.ordering.repositories.mock.MockQuoteRepository", "smpl.ordering.models.Quote", "smpl.ordering.repositories.mock.MockDealersRepository", "smpl.ordering.models.DealerInfo", "smpl.ordering.repositories.RepositoryFactory", "smpl.ordering.OrderingConfiguration", "smpl.ordering.repositories.mock.MockCatalogItemsRepository", "smpl.ordering.models.CatalogItem", "smpl.ordering.repositories.mock.MockOrderRepository", "smpl.ordering.repositories.mock.MockShipmentRepository", "smpl.ordering.repositories.mongodb.MongoCatalogItemsRepository", "smpl.ordering.repositories.mongodb.MongoOperationsWithRetry", "smpl.ordering.repositories.mongodb.MongoDealersRepository", "smpl.ordering.repositories.mongodb.MongoQuoteRepository", "smpl.ordering.repositories.mongodb.MongoOrderRepository", "smpl.ordering.repositories.mongodb.MongoShipmentRepository", "smpl.ordering.repositories.DealersRepositoryTest", "smpl.ordering.models.QuoteItemInfo", "smpl.ordering.BadRequestException"], "MockQuoteRepositoryTest_testRemoveQuote": ["smpl.ordering.models.Quote", "smpl.ordering.models.QuoteItemInfo", "smpl.ordering.repositories.QuoteRepositoryTest", "smpl.ordering.repositories.mock.MockQuoteRepository", "smpl.ordering.repositories.mock.MockDealersRepository", "smpl.ordering.models.DealerInfo", "smpl.ordering.repositories.mock.test.MockQuoteRepositoryTest", "smpl.ordering.BadRequestException", "smpl.ordering.repositories.RepositoryFactory", "smpl.ordering.OrderingConfiguration", "smpl.ordering.repositories.mock.MockCatalogItemsRepository", "smpl.ordering.models.CatalogItem", "smpl.ordering.repositories.mock.MockOrderRepository", "smpl.ordering.repositories.mock.MockShipmentRepository", "smpl.ordering.repositories.mongodb.MongoCatalogItemsRepository", "smpl.ordering.repositories.mongodb.MongoOperationsWithRetry", "smpl.ordering.repositories.mongodb.MongoDealersRepository", "smpl.ordering.repositories.mongodb.MongoQuoteRepository", "smpl.ordering.repositories.mongodb.MongoOrderRepository", "smpl.ordering.repositories.mongodb.MongoShipmentRepository", "smpl.ordering.repositories.DealersRepositoryTest"], "MockQuoteRepositoryTest_testGetQuotesByCustomerName": ["smpl.ordering.repositories.mock.test.MockQuoteRepositoryTest", "smpl.ordering.repositories.RepositoryFactory", "smpl.ordering.OrderingConfiguration", "smpl.ordering.repositories.mock.MockCatalogItemsRepository", "smpl.ordering.models.CatalogItem", "smpl.ordering.repositories.mock.MockDealersRepository", "smpl.ordering.repositories.mock.MockQuoteRepository", "smpl.ordering.repositories.mock.MockOrderRepository", "smpl.ordering.repositories.mock.MockShipmentRepository", "smpl.ordering.repositories.mongodb.MongoCatalogItemsRepository", "smpl.ordering.repositories.mongodb.MongoOperationsWithRetry", "smpl.ordering.repositories.mongodb.MongoDealersRepository", "smpl.ordering.repositories.mongodb.MongoQuoteRepository", "smpl.ordering.repositories.mongodb.MongoOrderRepository", "smpl.ordering.repositories.mongodb.MongoShipmentRepository", "smpl.ordering.repositories.QuoteRepositoryTest", "smpl.ordering.repositories.DealersRepositoryTest", "smpl.ordering.models.DealerInfo", "smpl.ordering.models.Quote", "smpl.ordering.models.QuoteItemInfo"], "QuoteControllerTest_testDeleteQuote": ["smpl.ordering.controllers.QuoteControllerTest", "smpl.ordering.repositories.RepositoryFactory", "smpl.ordering.OrderingConfiguration", "smpl.ordering.repositories.mock.MockCatalogItemsRepository", "smpl.ordering.models.CatalogItem", "smpl.ordering.repositories.mock.MockDealersRepository", "smpl.ordering.repositories.mock.MockQuoteRepository", "smpl.ordering.repositories.mock.MockOrderRepository", "smpl.ordering.repositories.mock.MockShipmentRepository", "smpl.ordering.repositories.mongodb.MongoCatalogItemsRepository", "smpl.ordering.repositories.mongodb.MongoOperationsWithRetry", "smpl.ordering.repositories.mongodb.MongoDealersRepository", "smpl.ordering.repositories.mongodb.MongoQuoteRepository", "smpl.ordering.repositories.mongodb.MongoOrderRepository", "smpl.ordering.repositories.mongodb.MongoShipmentRepository", "smpl.ordering.controllers.QuoteController", "smpl.ordering.repositories.QuoteRepositoryTest", "smpl.ordering.models.Quote", "smpl.ordering.models.QuoteItemInfo", "smpl.ordering.Utility", "smpl.ordering.models.DealerInfo", "smpl.ordering.OrderingInitializer"], "QuoteControllerTest_testUpdateQuote": ["smpl.ordering.OrderingInitializer", "smpl.ordering.models.Quote", "smpl.ordering.controllers.QuoteController", "smpl.ordering.repositories.RepositoryFactory", "smpl.ordering.repositories.mock.MockQuoteRepository", "smpl.ordering.controllers.QuoteControllerTest", "smpl.ordering.OrderingConfiguration", "smpl.ordering.repositories.mock.MockCatalogItemsRepository", "smpl.ordering.models.CatalogItem", "smpl.ordering.repositories.mock.MockDealersRepository", "smpl.ordering.repositories.mock.MockOrderRepository", "smpl.ordering.repositories.mock.MockShipmentRepository", "smpl.ordering.repositories.mongodb.MongoCatalogItemsRepository", "smpl.ordering.repositories.mongodb.MongoOperationsWithRetry", "smpl.ordering.repositories.mongodb.MongoDealersRepository", "smpl.ordering.repositories.mongodb.MongoQuoteRepository", "smpl.ordering.repositories.mongodb.MongoOrderRepository", "smpl.ordering.repositories.mongodb.MongoShipmentRepository", "smpl.ordering.repositories.QuoteRepositoryTest", "smpl.ordering.models.QuoteItemInfo", "smpl.ordering.Utility", "smpl.ordering.models.DealerInfo"], "QuoteControllerTest_testCreateQuote": ["smpl.ordering.repositories.mock.MockQuoteRepository", "smpl.ordering.models.Quote", "smpl.ordering.repositories.mock.MockDealersRepository", "smpl.ordering.models.DealerInfo", "smpl.ordering.controllers.QuoteController", "smpl.ordering.repositories.RepositoryFactory", "smpl.ordering.controllers.QuoteControllerTest", "smpl.ordering.OrderingConfiguration", "smpl.ordering.repositories.mock.MockCatalogItemsRepository", "smpl.ordering.models.CatalogItem", "smpl.ordering.repositories.mock.MockOrderRepository", "smpl.ordering.repositories.mock.MockShipmentRepository", "smpl.ordering.repositories.mongodb.MongoCatalogItemsRepository", "smpl.ordering.repositories.mongodb.MongoOperationsWithRetry", "smpl.ordering.repositories.mongodb.MongoDealersRepository", "smpl.ordering.repositories.mongodb.MongoQuoteRepository", "smpl.ordering.repositories.mongodb.MongoOrderRepository", "smpl.ordering.repositories.mongodb.MongoShipmentRepository", "smpl.ordering.repositories.QuoteRepositoryTest", "smpl.ordering.models.QuoteItemInfo", "smpl.ordering.Utility", "smpl.ordering.OrderingInitializer", "smpl.ordering.BadRequestException"], "QuoteControllerTest_testGetQuoteById": ["smpl.ordering.models.Quote", "smpl.ordering.repositories.mock.MockQuoteRepository", "smpl.ordering.OrderingInitializer", "smpl.ordering.controllers.QuoteController", "smpl.ordering.repositories.QuoteRepositoryTest", "smpl.ordering.models.QuoteItemInfo", "smpl.ordering.Utility", "smpl.ordering.repositories.RepositoryFactory", "smpl.ordering.repositories.mock.MockDealersRepository", "smpl.ordering.models.DealerInfo", "smpl.ordering.BadRequestException", "smpl.ordering.controllers.QuoteControllerTest", "smpl.ordering.OrderingConfiguration", "smpl.ordering.repositories.mock.MockCatalogItemsRepository", "smpl.ordering.models.CatalogItem", "smpl.ordering.repositories.mock.MockOrderRepository", "smpl.ordering.repositories.mock.MockShipmentRepository", "smpl.ordering.repositories.mongodb.MongoCatalogItemsRepository", "smpl.ordering.repositories.mongodb.MongoOperationsWithRetry", "smpl.ordering.repositories.mongodb.MongoDealersRepository", "smpl.ordering.repositories.mongodb.MongoQuoteRepository", "smpl.ordering.repositories.mongodb.MongoOrderRepository", "smpl.ordering.repositories.mongodb.MongoShipmentRepository"], "QuoteControllerTest_testGetQuotesByCustomerName": ["smpl.ordering.controllers.QuoteController", "smpl.ordering.models.Quote", "smpl.ordering.Utility", "smpl.ordering.repositories.RepositoryFactory", "smpl.ordering.repositories.mock.MockQuoteRepository", "smpl.ordering.repositories.mock.MockDealersRepository", "smpl.ordering.models.DealerInfo", "smpl.ordering.OrderingInitializer", "smpl.ordering.controllers.QuoteControllerTest", "smpl.ordering.OrderingConfiguration", "smpl.ordering.repositories.mock.MockCatalogItemsRepository", "smpl.ordering.models.CatalogItem", "smpl.ordering.repositories.mock.MockOrderRepository", "smpl.ordering.repositories.mock.MockShipmentRepository", "smpl.ordering.repositories.mongodb.MongoCatalogItemsRepository", "smpl.ordering.repositories.mongodb.MongoOperationsWithRetry", "smpl.ordering.repositories.mongodb.MongoDealersRepository", "smpl.ordering.repositories.mongodb.MongoQuoteRepository", "smpl.ordering.repositories.mongodb.MongoOrderRepository", "smpl.ordering.repositories.mongodb.MongoShipmentRepository", "smpl.ordering.repositories.QuoteRepositoryTest", "smpl.ordering.models.QuoteItemInfo"], "ShipmentControllerTest_testGetShipmentsByStatus": ["smpl.ordering.controllers.ShipmentControllerTest", "smpl.ordering.repositories.RepositoryFactory", "smpl.ordering.OrderingConfiguration", "smpl.ordering.repositories.mock.MockCatalogItemsRepository", "smpl.ordering.models.CatalogItem", "smpl.ordering.repositories.mock.MockDealersRepository", "smpl.ordering.repositories.mock.MockQuoteRepository", "smpl.ordering.repositories.mock.MockOrderRepository", "smpl.ordering.repositories.mock.MockShipmentRepository", "smpl.ordering.repositories.mongodb.MongoCatalogItemsRepository", "smpl.ordering.repositories.mongodb.MongoOperationsWithRetry", "smpl.ordering.repositories.mongodb.MongoDealersRepository", "smpl.ordering.repositories.mongodb.MongoQuoteRepository", "smpl.ordering.repositories.mongodb.MongoOrderRepository", "smpl.ordering.repositories.mongodb.MongoShipmentRepository", "smpl.ordering.repositories.QuoteRepositoryTest", "smpl.ordering.models.Quote", "smpl.ordering.models.QuoteItemInfo", "smpl.ordering.controllers.QuoteController", "smpl.ordering.Utility", "smpl.ordering.models.DealerInfo", "smpl.ordering.OrderingInitializer", "smpl.ordering.controllers.OrderController", "smpl.ordering.models.Order", "smpl.ordering.repositories.ShipmentRepositoryTest", "smpl.ordering.models.ShipmentRecord", "smpl.ordering.models.PhoneInfo", "smpl.ordering.models.DeliveryAddress", "smpl.ordering.controllers.ShipmentController", "smpl.ordering.models.OrderUpdateInfo", "smpl.ordering.models.OrderEventInfo"], "ShipmentControllerTest_testUpdateShipment": ["smpl.ordering.models.Order", "smpl.ordering.controllers.OrderController", "smpl.ordering.controllers.ShipmentControllerTest", "smpl.ordering.repositories.ShipmentRepositoryTest", "smpl.ordering.models.ShipmentRecord", "smpl.ordering.models.PhoneInfo", "smpl.ordering.models.DeliveryAddress", "smpl.ordering.controllers.ShipmentController", "smpl.ordering.repositories.RepositoryFactory", "smpl.ordering.repositories.mock.MockShipmentRepository", "smpl.ordering.repositories.mock.MockOrderRepository", "smpl.ordering.OrderingInitializer", "smpl.ordering.models.OrderUpdateInfo", "smpl.ordering.models.OrderEventInfo", "smpl.ordering.OrderingConfiguration", "smpl.ordering.repositories.mock.MockCatalogItemsRepository", "smpl.ordering.models.CatalogItem", "smpl.ordering.repositories.mock.MockDealersRepository", "smpl.ordering.repositories.mock.MockQuoteRepository", "smpl.ordering.repositories.mongodb.MongoCatalogItemsRepository", "smpl.ordering.repositories.mongodb.MongoOperationsWithRetry", "smpl.ordering.repositories.mongodb.MongoDealersRepository", "smpl.ordering.repositories.mongodb.MongoQuoteRepository", "smpl.ordering.repositories.mongodb.MongoOrderRepository", "smpl.ordering.repositories.mongodb.MongoShipmentRepository", "smpl.ordering.repositories.QuoteRepositoryTest", "smpl.ordering.models.Quote", "smpl.ordering.models.QuoteItemInfo", "smpl.ordering.controllers.QuoteController", "smpl.ordering.Utility", "smpl.ordering.models.DealerInfo"], "ShipmentControllerTest_testCreateShipment": ["smpl.ordering.controllers.ShipmentControllerTest", "smpl.ordering.repositories.RepositoryFactory", "smpl.ordering.OrderingConfiguration", "smpl.ordering.repositories.mock.MockCatalogItemsRepository", "smpl.ordering.models.CatalogItem", "smpl.ordering.repositories.mock.MockDealersRepository", "smpl.ordering.repositories.mock.MockQuoteRepository", "smpl.ordering.repositories.mock.MockOrderRepository", "smpl.ordering.repositories.mock.MockShipmentRepository", "smpl.ordering.repositories.mongodb.MongoCatalogItemsRepository", "smpl.ordering.repositories.mongodb.MongoOperationsWithRetry", "smpl.ordering.repositories.mongodb.MongoDealersRepository", "smpl.ordering.repositories.mongodb.MongoQuoteRepository", "smpl.ordering.repositories.mongodb.MongoOrderRepository", "smpl.ordering.repositories.mongodb.MongoShipmentRepository", "smpl.ordering.repositories.ShipmentRepositoryTest", "smpl.ordering.models.ShipmentRecord", "smpl.ordering.models.PhoneInfo", "smpl.ordering.models.DeliveryAddress", "smpl.ordering.controllers.ShipmentController", "smpl.ordering.BadRequestException", "smpl.ordering.repositories.QuoteRepositoryTest", "smpl.ordering.models.Quote", "smpl.ordering.models.QuoteItemInfo", "smpl.ordering.controllers.QuoteController", "smpl.ordering.Utility", "smpl.ordering.models.DealerInfo", "smpl.ordering.OrderingInitializer", "smpl.ordering.controllers.OrderController", "smpl.ordering.models.Order"], "ShipmentControllerTest_testGetAllShipments": ["smpl.ordering.controllers.ShipmentController", "smpl.ordering.repositories.RepositoryFactory", "smpl.ordering.models.ShipmentRecord", "smpl.ordering.repositories.mock.MockShipmentRepository", "smpl.ordering.repositories.mock.MockOrderRepository", "smpl.ordering.models.Order", "smpl.ordering.OrderingInitializer", "smpl.ordering.controllers.ShipmentControllerTest", "smpl.ordering.OrderingConfiguration", "smpl.ordering.repositories.mock.MockCatalogItemsRepository", "smpl.ordering.models.CatalogItem", "smpl.ordering.repositories.mock.MockDealersRepository", "smpl.ordering.repositories.mock.MockQuoteRepository", "smpl.ordering.repositories.mongodb.MongoCatalogItemsRepository", "smpl.ordering.repositories.mongodb.MongoOperationsWithRetry", "smpl.ordering.repositories.mongodb.MongoDealersRepository", "smpl.ordering.repositories.mongodb.MongoQuoteRepository", "smpl.ordering.repositories.mongodb.MongoOrderRepository", "smpl.ordering.repositories.mongodb.MongoShipmentRepository", "smpl.ordering.repositories.QuoteRepositoryTest", "smpl.ordering.models.Quote", "smpl.ordering.models.QuoteItemInfo", "smpl.ordering.controllers.QuoteController", "smpl.ordering.Utility", "smpl.ordering.models.DealerInfo", "smpl.ordering.controllers.OrderController", "smpl.ordering.repositories.ShipmentRepositoryTest", "smpl.ordering.models.PhoneInfo", "smpl.ordering.models.DeliveryAddress"], "ShipmentControllerTest_testAddEventToShipment": ["smpl.ordering.models.ShipmentRecord", "smpl.ordering.repositories.mock.MockOrderRepository", "smpl.ordering.models.Order", "smpl.ordering.repositories.mock.MockShipmentRepository", "smpl.ordering.OrderingInitializer", "smpl.ordering.controllers.ShipmentController", "smpl.ordering.repositories.RepositoryFactory", "smpl.ordering.controllers.ShipmentControllerTest", "smpl.ordering.OrderingConfiguration", "smpl.ordering.repositories.mock.MockCatalogItemsRepository", "smpl.ordering.models.CatalogItem", "smpl.ordering.repositories.mock.MockDealersRepository", "smpl.ordering.repositories.mock.MockQuoteRepository", "smpl.ordering.repositories.mongodb.MongoCatalogItemsRepository", "smpl.ordering.repositories.mongodb.MongoOperationsWithRetry", "smpl.ordering.repositories.mongodb.MongoDealersRepository", "smpl.ordering.repositories.mongodb.MongoQuoteRepository", "smpl.ordering.repositories.mongodb.MongoOrderRepository", "smpl.ordering.repositories.mongodb.MongoShipmentRepository", "smpl.ordering.repositories.QuoteRepositoryTest", "smpl.ordering.models.Quote", "smpl.ordering.models.QuoteItemInfo", "smpl.ordering.controllers.QuoteController", "smpl.ordering.Utility", "smpl.ordering.models.DealerInfo", "smpl.ordering.controllers.OrderController", "smpl.ordering.repositories.ShipmentRepositoryTest", "smpl.ordering.models.PhoneInfo", "smpl.ordering.models.DeliveryAddress", "smpl.ordering.models.ShipmentEventInfo"], "CatalogControllerTest_testAddCatalogItem": ["smpl.ordering.controllers.CatalogControllerTest", "smpl.ordering.repositories.RepositoryFactory", "smpl.ordering.OrderingConfiguration", "smpl.ordering.repositories.mock.MockCatalogItemsRepository", "smpl.ordering.models.CatalogItem", "smpl.ordering.repositories.mock.MockDealersRepository", "smpl.ordering.repositories.mock.MockQuoteRepository", "smpl.ordering.repositories.mock.MockOrderRepository", "smpl.ordering.repositories.mock.MockShipmentRepository", "smpl.ordering.repositories.mongodb.MongoCatalogItemsRepository", "smpl.ordering.repositories.mongodb.MongoOperationsWithRetry", "smpl.ordering.repositories.mongodb.MongoDealersRepository", "smpl.ordering.repositories.mongodb.MongoQuoteRepository", "smpl.ordering.repositories.mongodb.MongoOrderRepository", "smpl.ordering.repositories.mongodb.MongoShipmentRepository", "smpl.ordering.controllers.CatalogController", "smpl.ordering.Utility", "smpl.ordering.OrderingInitializer"], "CatalogControllerTest_testRemoveCatalogItem": ["smpl.ordering.controllers.CatalogControllerTest", "smpl.ordering.repositories.RepositoryFactory", "smpl.ordering.OrderingConfiguration", "smpl.ordering.repositories.mock.MockCatalogItemsRepository", "smpl.ordering.models.CatalogItem", "smpl.ordering.repositories.mock.MockDealersRepository", "smpl.ordering.repositories.mock.MockQuoteRepository", "smpl.ordering.repositories.mock.MockOrderRepository", "smpl.ordering.repositories.mock.MockShipmentRepository", "smpl.ordering.repositories.mongodb.MongoCatalogItemsRepository", "smpl.ordering.repositories.mongodb.MongoOperationsWithRetry", "smpl.ordering.repositories.mongodb.MongoDealersRepository", "smpl.ordering.repositories.mongodb.MongoQuoteRepository", "smpl.ordering.repositories.mongodb.MongoOrderRepository", "smpl.ordering.repositories.mongodb.MongoShipmentRepository", "smpl.ordering.controllers.CatalogController", "smpl.ordering.Utility", "smpl.ordering.OrderingInitializer"], "CatalogControllerTest_testGetCatalogItems": ["smpl.ordering.controllers.CatalogControllerTest", "smpl.ordering.repositories.RepositoryFactory", "smpl.ordering.OrderingConfiguration", "smpl.ordering.repositories.mock.MockCatalogItemsRepository", "smpl.ordering.models.CatalogItem", "smpl.ordering.repositories.mock.MockDealersRepository", "smpl.ordering.repositories.mock.MockQuoteRepository", "smpl.ordering.repositories.mock.MockOrderRepository", "smpl.ordering.repositories.mock.MockShipmentRepository", "smpl.ordering.repositories.mongodb.MongoCatalogItemsRepository", "smpl.ordering.repositories.mongodb.MongoOperationsWithRetry", "smpl.ordering.repositories.mongodb.MongoDealersRepository", "smpl.ordering.repositories.mongodb.MongoQuoteRepository", "smpl.ordering.repositories.mongodb.MongoOrderRepository", "smpl.ordering.repositories.mongodb.MongoShipmentRepository", "smpl.ordering.controllers.CatalogController", "smpl.ordering.Utility", "smpl.ordering.OrderingInitializer"], "CatalogControllerTest_testGetCatalogItem": ["smpl.ordering.models.CatalogItem", "smpl.ordering.repositories.mock.MockCatalogItemsRepository", "smpl.ordering.controllers.CatalogController", "smpl.ordering.controllers.CatalogControllerTest", "smpl.ordering.repositories.RepositoryFactory", "smpl.ordering.OrderingConfiguration", "smpl.ordering.repositories.mock.MockDealersRepository", "smpl.ordering.repositories.mock.MockQuoteRepository", "smpl.ordering.repositories.mock.MockOrderRepository", "smpl.ordering.repositories.mock.MockShipmentRepository", "smpl.ordering.repositories.mongodb.MongoCatalogItemsRepository", "smpl.ordering.repositories.mongodb.MongoOperationsWithRetry", "smpl.ordering.repositories.mongodb.MongoDealersRepository", "smpl.ordering.repositories.mongodb.MongoQuoteRepository", "smpl.ordering.repositories.mongodb.MongoOrderRepository", "smpl.ordering.repositories.mongodb.MongoShipmentRepository", "smpl.ordering.Utility", "smpl.ordering.OrderingInitializer"], "CatalogControllerTest_testUpsertCatalogItem": ["smpl.ordering.models.CatalogItem", "smpl.ordering.repositories.mock.MockCatalogItemsRepository", "smpl.ordering.controllers.CatalogController", "smpl.ordering.controllers.CatalogControllerTest", "smpl.ordering.repositories.RepositoryFactory", "smpl.ordering.OrderingConfiguration", "smpl.ordering.repositories.mock.MockDealersRepository", "smpl.ordering.repositories.mock.MockQuoteRepository", "smpl.ordering.repositories.mock.MockOrderRepository", "smpl.ordering.repositories.mock.MockShipmentRepository", "smpl.ordering.repositories.mongodb.MongoCatalogItemsRepository", "smpl.ordering.repositories.mongodb.MongoOperationsWithRetry", "smpl.ordering.repositories.mongodb.MongoDealersRepository", "smpl.ordering.repositories.mongodb.MongoQuoteRepository", "smpl.ordering.repositories.mongodb.MongoOrderRepository", "smpl.ordering.repositories.mongodb.MongoShipmentRepository", "smpl.ordering.Utility", "smpl.ordering.OrderingInitializer"], "DealerControllerTest_testUpdateDealer": ["smpl.ordering.controllers.DealerControllerTest", "smpl.ordering.repositories.RepositoryFactory", "smpl.ordering.OrderingConfiguration", "smpl.ordering.repositories.mock.MockCatalogItemsRepository", "smpl.ordering.models.CatalogItem", "smpl.ordering.repositories.mock.MockDealersRepository", "smpl.ordering.repositories.mock.MockQuoteRepository", "smpl.ordering.repositories.mock.MockOrderRepository", "smpl.ordering.repositories.mock.MockShipmentRepository", "smpl.ordering.repositories.mongodb.MongoCatalogItemsRepository", "smpl.ordering.repositories.mongodb.MongoOperationsWithRetry", "smpl.ordering.repositories.mongodb.MongoDealersRepository", "smpl.ordering.repositories.mongodb.MongoQuoteRepository", "smpl.ordering.repositories.mongodb.MongoOrderRepository", "smpl.ordering.repositories.mongodb.MongoShipmentRepository", "smpl.ordering.repositories.DealersRepositoryTest", "smpl.ordering.models.DealerInfo", "smpl.ordering.controllers.DealerController", "smpl.ordering.Utility", "smpl.ordering.OrderingInitializer"], "DealerControllerTest_testRemoveDealer": ["smpl.ordering.controllers.DealerControllerTest", "smpl.ordering.repositories.RepositoryFactory", "smpl.ordering.OrderingConfiguration", "smpl.ordering.repositories.mock.MockCatalogItemsRepository", "smpl.ordering.models.CatalogItem", "smpl.ordering.repositories.mock.MockDealersRepository", "smpl.ordering.repositories.mock.MockQuoteRepository", "smpl.ordering.repositories.mock.MockOrderRepository", "smpl.ordering.repositories.mock.MockShipmentRepository", "smpl.ordering.repositories.mongodb.MongoCatalogItemsRepository", "smpl.ordering.repositories.mongodb.MongoOperationsWithRetry", "smpl.ordering.repositories.mongodb.MongoDealersRepository", "smpl.ordering.repositories.mongodb.MongoQuoteRepository", "smpl.ordering.repositories.mongodb.MongoOrderRepository", "smpl.ordering.repositories.mongodb.MongoShipmentRepository", "smpl.ordering.repositories.DealersRepositoryTest", "smpl.ordering.models.DealerInfo", "smpl.ordering.controllers.DealerController", "smpl.ordering.Utility", "smpl.ordering.OrderingInitializer"], "DealerControllerTest_testAddDealer": ["smpl.ordering.controllers.DealerControllerTest", "smpl.ordering.repositories.RepositoryFactory", "smpl.ordering.OrderingConfiguration", "smpl.ordering.repositories.mock.MockCatalogItemsRepository", "smpl.ordering.models.CatalogItem", "smpl.ordering.repositories.mock.MockDealersRepository", "smpl.ordering.repositories.mock.MockQuoteRepository", "smpl.ordering.repositories.mock.MockOrderRepository", "smpl.ordering.repositories.mock.MockShipmentRepository", "smpl.ordering.repositories.mongodb.MongoCatalogItemsRepository", "smpl.ordering.repositories.mongodb.MongoOperationsWithRetry", "smpl.ordering.repositories.mongodb.MongoDealersRepository", "smpl.ordering.repositories.mongodb.MongoQuoteRepository", "smpl.ordering.repositories.mongodb.MongoOrderRepository", "smpl.ordering.repositories.mongodb.MongoShipmentRepository", "smpl.ordering.repositories.DealersRepositoryTest", "smpl.ordering.models.DealerInfo", "smpl.ordering.controllers.DealerController", "smpl.ordering.Utility", "smpl.ordering.OrderingInitializer"], "DealerControllerTest_testGetDealer": ["smpl.ordering.controllers.DealerController", "smpl.ordering.repositories.DealersRepositoryTest", "smpl.ordering.models.DealerInfo", "smpl.ordering.Utility", "smpl.ordering.repositories.RepositoryFactory", "smpl.ordering.repositories.mock.MockDealersRepository", "smpl.ordering.controllers.DealerControllerTest", "smpl.ordering.OrderingConfiguration", "smpl.ordering.repositories.mock.MockCatalogItemsRepository", "smpl.ordering.models.CatalogItem", "smpl.ordering.repositories.mock.MockQuoteRepository", "smpl.ordering.repositories.mock.MockOrderRepository", "smpl.ordering.repositories.mock.MockShipmentRepository", "smpl.ordering.repositories.mongodb.MongoCatalogItemsRepository", "smpl.ordering.repositories.mongodb.MongoOperationsWithRetry", "smpl.ordering.repositories.mongodb.MongoDealersRepository", "smpl.ordering.repositories.mongodb.MongoQuoteRepository", "smpl.ordering.repositories.mongodb.MongoOrderRepository", "smpl.ordering.repositories.mongodb.MongoShipmentRepository", "smpl.ordering.OrderingInitializer"], "DealerControllerTest_testGetDealers": ["smpl.ordering.repositories.mock.MockCatalogItemsRepository", "smpl.ordering.models.CatalogItem", "smpl.ordering.repositories.mock.MockDealersRepository", "smpl.ordering.repositories.mock.MockQuoteRepository", "smpl.ordering.repositories.mock.MockOrderRepository", "smpl.ordering.repositories.mock.MockShipmentRepository", "smpl.ordering.repositories.mongodb.MongoCatalogItemsRepository", "smpl.ordering.repositories.mongodb.MongoOperationsWithRetry", "smpl.ordering.repositories.mongodb.MongoDealersRepository", "smpl.ordering.repositories.mongodb.MongoQuoteRepository", "smpl.ordering.repositories.mongodb.MongoOrderRepository", "smpl.ordering.repositories.mongodb.MongoShipmentRepository", "smpl.ordering.repositories.RepositoryFactory", "smpl.ordering.controllers.DealerControllerTest", "smpl.ordering.controllers.DealerController", "smpl.ordering.repositories.DealersRepositoryTest", "smpl.ordering.models.DealerInfo", "smpl.ordering.Utility", "smpl.ordering.OrderingInitializer", "smpl.ordering.OrderingConfiguration"], "OrderControllerTest_testGetQuotesByDealerName": ["smpl.ordering.controllers.OrderControllerTest", "smpl.ordering.repositories.RepositoryFactory", "smpl.ordering.OrderingConfiguration", "smpl.ordering.repositories.mock.MockCatalogItemsRepository", "smpl.ordering.models.CatalogItem", "smpl.ordering.repositories.mock.MockDealersRepository", "smpl.ordering.repositories.mock.MockQuoteRepository", "smpl.ordering.repositories.mock.MockOrderRepository", "smpl.ordering.repositories.mock.MockShipmentRepository", "smpl.ordering.repositories.mongodb.MongoCatalogItemsRepository", "smpl.ordering.repositories.mongodb.MongoOperationsWithRetry", "smpl.ordering.repositories.mongodb.MongoDealersRepository", "smpl.ordering.repositories.mongodb.MongoQuoteRepository", "smpl.ordering.repositories.mongodb.MongoOrderRepository", "smpl.ordering.repositories.mongodb.MongoShipmentRepository", "smpl.ordering.controllers.OrderController", "smpl.ordering.repositories.QuoteRepositoryTest", "smpl.ordering.models.Quote", "smpl.ordering.models.QuoteItemInfo", "smpl.ordering.controllers.QuoteController", "smpl.ordering.Utility", "smpl.ordering.models.DealerInfo", "smpl.ordering.OrderingInitializer", "smpl.ordering.models.Order"], "OrderControllerTest_testCreateOrder": ["smpl.ordering.repositories.RepositoryFactory", "smpl.ordering.controllers.OrderController", "smpl.ordering.repositories.mock.MockOrderRepository", "smpl.ordering.models.Order", "smpl.ordering.controllers.OrderControllerTest", "smpl.ordering.OrderingConfiguration", "smpl.ordering.repositories.mock.MockCatalogItemsRepository", "smpl.ordering.models.CatalogItem", "smpl.ordering.repositories.mock.MockDealersRepository", "smpl.ordering.repositories.mock.MockQuoteRepository", "smpl.ordering.repositories.mock.MockShipmentRepository", "smpl.ordering.repositories.mongodb.MongoCatalogItemsRepository", "smpl.ordering.repositories.mongodb.MongoOperationsWithRetry", "smpl.ordering.repositories.mongodb.MongoDealersRepository", "smpl.ordering.repositories.mongodb.MongoQuoteRepository", "smpl.ordering.repositories.mongodb.MongoOrderRepository", "smpl.ordering.repositories.mongodb.MongoShipmentRepository", "smpl.ordering.repositories.QuoteRepositoryTest", "smpl.ordering.models.Quote", "smpl.ordering.models.QuoteItemInfo", "smpl.ordering.controllers.QuoteController", "smpl.ordering.Utility", "smpl.ordering.models.DealerInfo", "smpl.ordering.OrderingInitializer"], "OrderControllerTest_testAddEvent": ["smpl.ordering.repositories.RepositoryFactory", "smpl.ordering.controllers.OrderController", "smpl.ordering.repositories.mock.MockOrderRepository", "smpl.ordering.models.Order", "smpl.ordering.controllers.OrderControllerTest", "smpl.ordering.OrderingConfiguration", "smpl.ordering.repositories.mock.MockCatalogItemsRepository", "smpl.ordering.models.CatalogItem", "smpl.ordering.repositories.mock.MockDealersRepository", "smpl.ordering.repositories.mock.MockQuoteRepository", "smpl.ordering.repositories.mock.MockShipmentRepository", "smpl.ordering.repositories.mongodb.MongoCatalogItemsRepository", "smpl.ordering.repositories.mongodb.MongoOperationsWithRetry", "smpl.ordering.repositories.mongodb.MongoDealersRepository", "smpl.ordering.repositories.mongodb.MongoQuoteRepository", "smpl.ordering.repositories.mongodb.MongoOrderRepository", "smpl.ordering.repositories.mongodb.MongoShipmentRepository", "smpl.ordering.repositories.QuoteRepositoryTest", "smpl.ordering.models.Quote", "smpl.ordering.models.QuoteItemInfo", "smpl.ordering.controllers.QuoteController", "smpl.ordering.Utility", "smpl.ordering.models.DealerInfo", "smpl.ordering.OrderingInitializer", "smpl.ordering.models.OrderEventInfo"], "OrderControllerTest_testGetOrderById": ["smpl.ordering.models.Order", "smpl.ordering.models.OrderEventInfo", "smpl.ordering.controllers.OrderControllerTest", "smpl.ordering.repositories.RepositoryFactory", "smpl.ordering.OrderingConfiguration", "smpl.ordering.repositories.mock.MockCatalogItemsRepository", "smpl.ordering.models.CatalogItem", "smpl.ordering.repositories.mock.MockDealersRepository", "smpl.ordering.repositories.mock.MockQuoteRepository", "smpl.ordering.repositories.mock.MockOrderRepository", "smpl.ordering.repositories.mock.MockShipmentRepository", "smpl.ordering.repositories.mongodb.MongoCatalogItemsRepository", "smpl.ordering.repositories.mongodb.MongoOperationsWithRetry", "smpl.ordering.repositories.mongodb.MongoDealersRepository", "smpl.ordering.repositories.mongodb.MongoQuoteRepository", "smpl.ordering.repositories.mongodb.MongoOrderRepository", "smpl.ordering.repositories.mongodb.MongoShipmentRepository", "smpl.ordering.controllers.OrderController", "smpl.ordering.repositories.QuoteRepositoryTest", "smpl.ordering.models.Quote", "smpl.ordering.models.QuoteItemInfo", "smpl.ordering.controllers.QuoteController", "smpl.ordering.Utility", "smpl.ordering.models.DealerInfo", "smpl.ordering.OrderingInitializer"], "OrderControllerTest_testUpdate": ["smpl.ordering.models.Order", "smpl.ordering.models.OrderEventInfo", "smpl.ordering.controllers.OrderControllerTest", "smpl.ordering.repositories.RepositoryFactory", "smpl.ordering.OrderingConfiguration", "smpl.ordering.repositories.mock.MockCatalogItemsRepository", "smpl.ordering.models.CatalogItem", "smpl.ordering.repositories.mock.MockDealersRepository", "smpl.ordering.repositories.mock.MockQuoteRepository", "smpl.ordering.repositories.mock.MockOrderRepository", "smpl.ordering.repositories.mock.MockShipmentRepository", "smpl.ordering.repositories.mongodb.MongoCatalogItemsRepository", "smpl.ordering.repositories.mongodb.MongoOperationsWithRetry", "smpl.ordering.repositories.mongodb.MongoDealersRepository", "smpl.ordering.repositories.mongodb.MongoQuoteRepository", "smpl.ordering.repositories.mongodb.MongoOrderRepository", "smpl.ordering.repositories.mongodb.MongoShipmentRepository", "smpl.ordering.controllers.OrderController", "smpl.ordering.repositories.QuoteRepositoryTest", "smpl.ordering.models.Quote", "smpl.ordering.models.QuoteItemInfo", "smpl.ordering.controllers.QuoteController", "smpl.ordering.Utility", "smpl.ordering.models.DealerInfo", "smpl.ordering.OrderingInitializer", "smpl.ordering.models.OrderUpdateInfo"], "integration": ["integration.Main", "integration.scheduled.CreateOrderProcessTask", "integration.infrastructure.ConfigurationManager", "integration.infrastructure.ConfigurationHelpers", "integration.services.MrpConnectService", "integration.services.QueueService", "integration.services.QueueFactory", "integration.scheduled.UpdateProductProcessTask"], "ordering": ["smpl.ordering.OrderingConfiguration", "smpl.ordering.OrderingServiceProperties", "smpl.ordering.MongoDBProperties", "smpl.ordering.Utility", "smpl.ordering.AppInsightsFilter", "smpl.ordering.SimpleCORSFilter", "smpl.ordering.repositories.RepositoryFactory", "smpl.ordering.repositories.mock.MockCatalogItemsRepository", "smpl.ordering.models.CatalogItem", "smpl.ordering.repositories.mock.MockDealersRepository", "smpl.ordering.repositories.mock.MockQuoteRepository", "smpl.ordering.repositories.mock.MockOrderRepository", "smpl.ordering.repositories.mock.MockShipmentRepository", "smpl.ordering.repositories.mongodb.MongoCatalogItemsRepository", "smpl.ordering.repositories.mongodb.MongoOperationsWithRetry", "smpl.ordering.repositories.mongodb.MongoDealersRepository", "smpl.ordering.repositories.mongodb.MongoQuoteRepository", "smpl.ordering.repositories.mongodb.MongoOrderRepository", "smpl.ordering.repositories.mongodb.MongoShipmentRepository", "smpl.ordering.controllers.CatalogController", "smpl.ordering.controllers.DealerController", "smpl.ordering.controllers.OrderController", "smpl.ordering.controllers.ShipmentController", "smpl.ordering.controllers.QuoteController"]}